sphinxcontrib/__init__.py
sphinxcontrib/swaggerdoc/__init__.py
sphinxcontrib/swaggerdoc/swagger_doc.py
sphinxcontrib/swaggerdoc/swaggerv2_doc.py
sphinxcontrib_swaggerdoc-0.1.7.dist-info/DESCRIPTION.rst
sphinxcontrib_swaggerdoc-0.1.7.dist-info/METADATA
sphinxcontrib_swaggerdoc-0.1.7.dist-info/RECORD
sphinxcontrib_swaggerdoc-0.1.7.dist-info/WHEEL
sphinxcontrib_swaggerdoc-0.1.7.dist-info/metadata.json
sphinxcontrib_swaggerdoc-0.1.7.dist-info/top_level.txt
