Metadata-Version: 2.0
Name: sphinxcontrib-swaggerdoc
Version: 0.1.7
Summary: Sphinx extension for documenting Swagger 2.0 APIs
Home-page: https://github.com/unaguil/sphinx-swaggerdoc
Author: Unai Aguilera
Author-email: unai.aguilera@deusto.es
License: MIT
Platform: UNKNOWN
Classifier: Development Status :: 4 - Beta
Classifier: Environment :: Console
Classifier: Environment :: Web Environment
Classifier: Intended Audience :: Developers
Classifier: Operating System :: OS Independent
Classifier: License :: OSI Approved :: MIT License
Classifier: Programming Language :: Python
Classifier: Topic :: Documentation
Classifier: Topic :: Utilities
Requires-Dist: sphinx
Requires-Dist: requests
Requires-Dist: requests-file
Requires-Dist: future
